AUTHORS
Changelog
INSTALL
LICENSE
MANIFEST.in
README
README.rst
TODO
setup.cfg
setup.py
docs/.DS_Store
docs/.conf.py.swp
docs/.index.rst.swp
docs/Makefile
docs/changelog.rst
docs/conf.py
docs/index.rst
docs/introduction.rst
docs/.build/doctrees/changelog.doctree
docs/.build/doctrees/environment.pickle
docs/.build/doctrees/index.doctree
docs/.build/doctrees/introduction.doctree
docs/.build/doctrees/reference/index.doctree
docs/.build/doctrees/reference/timer.doctree
docs/.build/doctrees/reference/timer2.doctree
docs/.build/html/.buildinfo
docs/.build/html/changelog.html
docs/.build/html/genindex.html
docs/.build/html/index.html
docs/.build/html/introduction.html
docs/.build/html/objects.inv
docs/.build/html/py-modindex.html
docs/.build/html/search.html
docs/.build/html/searchindex.js
docs/.build/html/reference/index.html
docs/.build/html/reference/timer2.html
docs/.build/html/sources/changelog.txt
docs/.build/html/sources/index.txt
docs/.build/html/sources/introduction.txt
docs/.build/html/sources/reference/index.txt
docs/.build/html/sources/reference/timer2.txt
docs/.build/html/static/basic.css
docs/.build/html/static/celery.css
docs/.build/html/static/doctools.js
docs/.build/html/static/file.png
docs/.build/html/static/jquery.js
docs/.build/html/static/minus.png
docs/.build/html/static/plus.png
docs/.build/html/static/pygments.css
docs/.build/html/static/searchtools.js
docs/.build/html/static/underscore.js
docs/.static/.keep
docs/.templates/.sidebarintro.html.swp
docs/.templates/.sidebarlogo.html.swp
docs/.templates/sidebarintro.html
docs/.templates/sidebarlogo.html
docs/_ext/applyxrefs.py
docs/_ext/literals_to_xrefs.py
docs/_theme/celery/theme.conf
docs/_theme/celery/static/celery.css_t
docs/images/timer.jpg
docs/reference/.index.rst.swp
docs/reference/.timer2.rst.swp
docs/reference/index.rst
docs/reference/timer2.rst
timer2/__init__.py
timer2.egg-info/PKG-INFO
timer2.egg-info/SOURCES.txt
timer2.egg-info/dependency_links.txt
timer2.egg-info/not-zip-safe
timer2.egg-info/top_level.txt
timer2/tests/__init__.py